MANIFEST.in
README.md
setup.py
nose-1.3.0-py2.7.egg/EGG-INFO/SOURCES.txt
nose-1.3.0-py2.7.egg/EGG-INFO/dependency_links.txt
nose-1.3.0-py2.7.egg/EGG-INFO/entry_points.txt
nose-1.3.0-py2.7.egg/EGG-INFO/top_level.txt
nose-1.3.0-py2.7.egg/nose/__init__.py
nose-1.3.0-py2.7.egg/nose/__main__.py
nose-1.3.0-py2.7.egg/nose/case.py
nose-1.3.0-py2.7.egg/nose/commands.py
nose-1.3.0-py2.7.egg/nose/config.py
nose-1.3.0-py2.7.egg/nose/core.py
nose-1.3.0-py2.7.egg/nose/exc.py
nose-1.3.0-py2.7.egg/nose/failure.py
nose-1.3.0-py2.7.egg/nose/importer.py
nose-1.3.0-py2.7.egg/nose/inspector.py
nose-1.3.0-py2.7.egg/nose/loader.py
nose-1.3.0-py2.7.egg/nose/proxy.py
nose-1.3.0-py2.7.egg/nose/pyversion.py
nose-1.3.0-py2.7.egg/nose/result.py
nose-1.3.0-py2.7.egg/nose/selector.py
nose-1.3.0-py2.7.egg/nose/suite.py
nose-1.3.0-py2.7.egg/nose/twistedtools.py
nose-1.3.0-py2.7.egg/nose/usage.txt
nose-1.3.0-py2.7.egg/nose/util.py
nose-1.3.0-py2.7.egg/nose/ext/__init__.py
nose-1.3.0-py2.7.egg/nose/ext/dtcompat.py
nose-1.3.0-py2.7.egg/nose/plugins/__init__.py
nose-1.3.0-py2.7.egg/nose/plugins/allmodules.py
nose-1.3.0-py2.7.egg/nose/plugins/attrib.py
nose-1.3.0-py2.7.egg/nose/plugins/base.py
nose-1.3.0-py2.7.egg/nose/plugins/builtin.py
nose-1.3.0-py2.7.egg/nose/plugins/capture.py
nose-1.3.0-py2.7.egg/nose/plugins/collect.py
nose-1.3.0-py2.7.egg/nose/plugins/cover.py
nose-1.3.0-py2.7.egg/nose/plugins/debug.py
nose-1.3.0-py2.7.egg/nose/plugins/deprecated.py
nose-1.3.0-py2.7.egg/nose/plugins/doctests.py
nose-1.3.0-py2.7.egg/nose/plugins/errorclass.py
nose-1.3.0-py2.7.egg/nose/plugins/failuredetail.py
nose-1.3.0-py2.7.egg/nose/plugins/isolate.py
nose-1.3.0-py2.7.egg/nose/plugins/logcapture.py
nose-1.3.0-py2.7.egg/nose/plugins/manager.py
nose-1.3.0-py2.7.egg/nose/plugins/multiprocess.py
nose-1.3.0-py2.7.egg/nose/plugins/plugintest.py
nose-1.3.0-py2.7.egg/nose/plugins/prof.py
nose-1.3.0-py2.7.egg/nose/plugins/skip.py
nose-1.3.0-py2.7.egg/nose/plugins/testid.py
nose-1.3.0-py2.7.egg/nose/plugins/xunit.py
nose-1.3.0-py2.7.egg/nose/sphinx/__init__.py
nose-1.3.0-py2.7.egg/nose/sphinx/pluginopts.py
nose-1.3.0-py2.7.egg/nose/tools/__init__.py
nose-1.3.0-py2.7.egg/nose/tools/nontrivial.py
src/underpy.egg-info/PKG-INFO
src/underpy.egg-info/SOURCES.txt
src/underpy.egg-info/dependency_links.txt
src/underpy.egg-info/not-zip-safe
src/underpy.egg-info/requires.txt
src/underpy.egg-info/top_level.txt