Metadata-Version: 1.1
Name: underpy
Version: 0.1.2
Summary: Functional helpers for Python
Home-page: https://github.com/ramonski/underpy
Author: Ramon Bartl
Author-email: ramon.bartl@googlemail.com
License: MIT
Platform: any
Classifier: Programming Language :: Python
Classifier: Intended Audience :: Developers
Classifier: Operating System :: OS Independent
Classifier: Topic :: Software Development :: Libraries :: Python Modules
